static_calculator/__init__.py
static_calculator/add.py
static_calculator/subtract.py
stats_calculator_chamso-0.1.0.dist-info/METADATA
stats_calculator_chamso-0.1.0.dist-info/WHEEL
stats_calculator_chamso-0.1.0.dist-info/entry_points.txt
stats_calculator_chamso-0.1.0.dist-info/RECORD
